tclaude/__init__.py
tclaude/__main__.py
tclaude/chat.py
tclaude/commands.py
tclaude/common.py
tclaude/config.py
tclaude/endpoints.py
tclaude/event.py
tclaude/files.py
tclaude/json.py
tclaude/live_print.py
tclaude/logging_config.py
tclaude/mcp.py
tclaude/oauth.py
tclaude/print.py
tclaude/prompt.py
tclaude/session.py
tclaude/spinner.py
tclaude/task_context.py
tclaude/tclaude.py
tclaude/terminal_prompt.py
tclaude/token_counter.py
tclaude/tool_use.py
tclaude/tools.py
tclaude/default-config/tclaude.toml
tclaude-1.0.2.dist-info/licenses/LICENSE.txt
tclaude-1.0.2.dist-info/METADATA
tclaude-1.0.2.dist-info/WHEEL
tclaude-1.0.2.dist-info/entry_points.txt
tclaude-1.0.2.dist-info/top_level.txt
tclaude-1.0.2.dist-info/RECORD
