Metadata-Version: 2.4
Name: tclaude
Version: 1.0.2
Summary: A complete terminal implementation of Anthropic's Claude.
Author-email: Thomas Müller <tom@94.me>
License-Expression: GPL-3.0-only
Project-URL: Repository, https://github.com/Tom94/tclaude
Classifier: Development Status :: 5 - Production/Stable
Classifier: Intended Audience :: Developers
Classifier: Intended Audience :: End Users/Desktop
Classifier: Topic :: Communications :: Chat
Classifier: Topic :: Scientific/Engineering :: Artificial Intelligence
Classifier: Topic :: Software Development :: Libraries :: Python Modules
Classifier: Topic :: Utilities
Classifier: Programming Language :: Python :: 3.12
Classifier: Programming Language :: Python :: 3.13
Classifier: Programming Language :: Python :: 3.14
Classifier: Environment :: Console
Classifier: Operating System :: OS Independent
Classifier: Natural Language :: English
Requires-Python: >=3.12
License-File: LICENSE.txt
Requires-Dist: aiofiles
Requires-Dist: aiohttp
Requires-Dist: beautifulsoup4
Requires-Dist: docstring_parser
Requires-Dist: html2text
Requires-Dist: humanize
Requires-Dist: keyring
Requires-Dist: mcp
Requires-Dist: oauthlib
Requires-Dist: partial-json-parser
Requires-Dist: prompt_toolkit
Requires-Dist: wcwidth
Dynamic: license-file
